{"package_name": "elasticsearch", "latest_version": "9.4.1", "summary": "Python client for Elasticsearch", "requires_python": ">=3.10", "monthly_downloads": 54267183, "downloads_status": "LIVE", "downloads_last_verified_at": "2026-07-18T06:07:23.518196+00:00", "github_repo_url": "https://github.com/elastic/elasticsearch-py", "risk_score": 0.5, "risk_label": "LOW", "trend_direction": "STABLE", "score_version": 1, "components": {"maintainer": 0.0, "cve": 0.0, "depth": 0.0, "downloads": 0.5}, "maintainer": {"status": "LIVE", "last_verified_at": "2026-07-18T06:07:23.518196+00:00", "last_commit_at": "2026-07-17T14:27:11+00:00", "days_since_last_commit": 1, "commit_count_90d": 26, "contributors_count": 2425, "is_archived": false, "activity_label": "ACTIVE"}, "cves": [], "trend_history": [{"date": "2026-06", "risk_score": 0.5}, {"date": "2026-07", "risk_score": 0.5}], "blast_radius_count": 0, "direct_dependents": [], "direct_dependencies": ["anyio", "elastic-transport", "python-dateutil", "sniffio", "typing-extensions", "pyarrow"]}