{"package_name": "huggingface-hub", "latest_version": "1.13.0", "summary": "Client library to download and publish models, datasets and other repos on the huggingface.co hub", "requires_python": ">=3.10.0", "monthly_downloads": null, "github_repo_url": "https://github.com/huggingface/huggingface_hub", "risk_score": 4.9, "risk_label": "MEDIUM", "trend_direction": "STABLE", "score_version": 1, "components": {"maintainer": 4.0, "cve": 0.0, "depth": 0.4, "downloads": 0.5}, "maintainer": {"last_commit_at": null, "days_since_last_commit": null, "commit_count_90d": null, "contributors_count": null, "is_archived": null, "activity_label": null}, "cves": [], "trend_history": [{"date": "2026-05", "risk_score": 4.9}], "blast_radius_count": 10, "direct_dependents": ["datasets", "transformers", "pyiceberg", "sentry-sdk", "accelerate", "safetensors", "tokenizers", "pydantic-ai-slim", "sentence-transformers", "universal-pathlib"], "direct_dependencies": ["authlib", "typing-extensions", "pytest", "fsspec", "mypy", "libcst", "hf-xet", "pyyaml", "tqdm", "httpx", "ruff", "packaging", "urllib3", "pytest-rerunfailures", "filelock", "mcp", "fastcore", "torch", "typer", "jinja2", "requests", "fastapi", "pytest-mock", "jedi", "pytest-asyncio", "types-pyyaml", "types-urllib3", "numpy", "toml", "safetensors", "pytest-xdist", "itsdangerous", "duckdb", "ty", "pillow", "pytest-cov", "types-toml", "pytest-env"]}