{"package_name": "jeepney", "latest_version": "0.9.0", "summary": "Low-level, pure Python DBus protocol wrapper.", "requires_python": ">=3.7", "monthly_downloads": null, "github_repo_url": null, "risk_score": 2.9, "risk_label": "LOW", "trend_direction": "STABLE", "score_version": 1, "components": {"maintainer": 2.0, "cve": 0.0, "depth": 0.4, "downloads": 0.5}, "maintainer": null, "cves": [], "trend_history": [{"date": "2026-05", "risk_score": 2.9}], "blast_radius_count": 2, "direct_dependents": ["keyring", "secretstorage"], "direct_dependencies": ["pytest-asyncio", "trio", "pytest", "async-timeout"]}