{"package_name": "wrapt", "latest_version": "2.1.2", "summary": "Module for decorators, wrappers and monkey patching.", "requires_python": ">=3.9", "monthly_downloads": null, "github_repo_url": "https://github.com/GrahamDumpleton/wrapt", "risk_score": 5.3, "risk_label": "HIGH", "trend_direction": "STABLE", "score_version": 1, "components": {"maintainer": 4.0, "cve": 0.0, "depth": 0.8, "downloads": 0.5}, "maintainer": {"last_commit_at": null, "days_since_last_commit": null, "commit_count_90d": null, "contributors_count": null, "is_archived": null, "activity_label": null}, "cves": [], "trend_history": [{"date": "2026-05", "risk_score": 5.3}], "blast_radius_count": 13, "direct_dependents": ["opentelemetry-instrumentation", "deprecated", "aiobotocore", "ddtrace", "langfuse", "opentelemetry-instrumentation-aiohttp-client", "opentelemetry-instrumentation-dbapi", "opentelemetry-instrumentation-httpx", "opentelemetry-instrumentation-threading", "smart-open"], "direct_dependencies": []}